hypothepy/__init__.py
hypothepy/cli.py
hypothepy/hypothepy.py
hypothepy/utils/__init__.py
hypothepy/utils/functions.py
hypothepy/utils/http_client.py
hypothepy/v1/__init__.py
hypothepy/v1/api.py
hypothepy/v1/common.py
hypothepy/v1/helpers.py
hypothepy/v1/endpoints/__init__.py
hypothepy/v1/endpoints/annotations.py
hypothepy/v1/endpoints/general.py
hypothepy/v1/endpoints/groups.py
hypothepy/v1/endpoints/profile.py
tests/hypothepy/__init__.py
tests/hypothepy/utils/__init__.py
tests/hypothepy/utils/test_http_client.py
tests/hypothepy/v1/__init__.py
tests/hypothepy/v1/common.py
tests/hypothepy/v1/test_helpers.py
tests/hypothepy/v1/endpoints/__init__.py
tests/hypothepy/v1/endpoints/test_annotations.py
tests/hypothepy/v1/endpoints/test_general.py
tests/hypothepy/v1/endpoints/test_groups.py
tests/hypothepy/v1/endpoints/test_profile.py
hypothepy-0.3.0.dist-info/AUTHORS.rst
hypothepy-0.3.0.dist-info/LICENSE
hypothepy-0.3.0.dist-info/METADATA
hypothepy-0.3.0.dist-info/WHEEL
hypothepy-0.3.0.dist-info/entry_points.txt
hypothepy-0.3.0.dist-info/top_level.txt
hypothepy-0.3.0.dist-info/RECORD
