Metadata-Version: 2.1
Name: hypothepy
Version: 0.3.0
Summary: A lightweight Python API for Hypothes.is
Home-page: https://github.com/embo-press/hypothepy
Author: EMBO
Author-email: embo_dev@embo.org
License: MIT license
Keywords: hypothepy
Platform: UNKNOWN
Classifier: Development Status :: 2 - Pre-Alpha
Classifier: Intended Audience :: Developers
Classifier: License :: OSI Approved :: MIT License
Classifier: Natural Language :: English
Classifier: Programming Language :: Python :: 3
Classifier: Programming Language :: Python :: 3.6
Classifier: Programming Language :: Python :: 3.7
Requires-Dist: Click (>=6.0)
